{
  "modified_date": "2018-02-17T21:40:52.748Z",
  "poloniex": {
    "btc_steem": "0.00039664",
    "btc_sbd": "0.00046092",
    "trading_fee_per": "0.0025",
    "transfer_fee_btc": "0.0001",
    "withdraw_fee_steem": "0.01",
    "withdraw_fee_sbd": "0.01"
  },
  "bittrex": {
    "btc_steem": "0.00041045",
    "btc_sbd": "0.00050011",
    "trading_fee_per": "0.0025",
    "transfer_fee_btc": "0.0001",
    "withdraw_fee_steem": "0.01",
    "withdraw_fee_sbd": "0.01"
  },
  "bithumb": {
    "btc_krw": "12088000",
    "trading_fee_per": "0.0015",
    "transfer_fee_btc": "0.0005",
    "withdraw_fee_krw": "1000"
  },
  "korbit": {
    "btc_krw": "12081500",
    "trading_fee_per": "0.002",
    "transfer_fee_btc": "0.001",
    "withdraw_fee_krw": "1000"
  },
  "coinone": {
    "trading_fee_per": "0.0015",
    "transfer_fee_btc": "0.0005",
    "withdraw_fee_krw": "1000",
    "btc_krw": "12072000"
  }
}